nextpertise_envy_settings/__init__.py
nextpertise_envy_settings-0.4.0.dist-info/METADATA
nextpertise_envy_settings-0.4.0.dist-info/WHEEL
nextpertise_envy_settings-0.4.0.dist-info/RECORD
