Metadata-Version: 2.3
Name: nextpertise-envy-settings
Version: 0.4.0
Summary: Reusable settings loader for Keycloak-secured Envy environments
License: MIT
Author: Len van Essen
Author-email: len@wndr.digital
Requires-Python: >=3.9,<4.0
Classifier: License :: OSI Approved :: MIT License
Classifier: Programming Language :: Python :: 3
Classifier: Programming Language :: Python :: 3.9
Classifier: Programming Language :: Python :: 3.10
Classifier: Programming Language :: Python :: 3.11
Classifier: Programming Language :: Python :: 3.12
Classifier: Programming Language :: Python :: 3.13
Requires-Dist: pydantic (>=2.10.1,<3.0.0)
Requires-Dist: pydantic-settings (>=2.0.0,<3.0.0)
Requires-Dist: requests (>=2.31,<3.0)
